notrans.py
notrans_python-1.0.0.dist-info/LICENSE
notrans_python-1.0.0.dist-info/METADATA
notrans_python-1.0.0.dist-info/WHEEL
notrans_python-1.0.0.dist-info/top_level.txt
notrans_python-1.0.0.dist-info/RECORD
