Metadata-Version: 2.1
Name: notrans-python
Version: 1.0.0
Summary: Corrects gendered language
Author-email: notrans <notrans@protonmail.com>
Project-URL: Homepage, https://github.com/notrans/notrans-python
Project-URL: Bug Tracker, https://github.com/notrans/notrans-python/issues
Classifier: Programming Language :: Python :: 3
Classifier: License :: OSI Approved :: MIT License
Classifier: Operating System :: OS Independent
Requires-Python: >=3.7
License-File: LICENSE
